pydocenhancer/__init__.py
pydocenhancer/__version__.py
pydocenhancer/cli.py
pydocenhancer/core.py
pydocenhancer-3.3.0.dist-info/licenses/LICENSE
tests/__init__.py
tests/test_core.py
pydocenhancer-3.3.0.dist-info/METADATA
pydocenhancer-3.3.0.dist-info/WHEEL
pydocenhancer-3.3.0.dist-info/entry_points.txt
pydocenhancer-3.3.0.dist-info/top_level.txt
pydocenhancer-3.3.0.dist-info/RECORD
