Metadata-Version: 2.4
Name: pydocenhancer
Version: 3.3.0
Summary: AI-powered Python documentation enhancer supporting local LLMs (LLaMA, Ollama) and cloud providers.
Home-page: https://github.com/utachicodes/PyDocEnhancer
Author: Abdoullah Ndao
Author-email: Abdoullah Ndao <abdoullahaljersi@gmail.com>
License: MIT
Project-URL: Homepage, https://github.com/utachicodes/PyDocEnhancer
Project-URL: Documentation, https://github.com/utachicodes/PyDocEnhancer#readme
Requires-Python: >=3.8
License-File: LICENSE
Requires-Dist: sentence-transformers>=2.2.2
Requires-Dist: click>=8.1.0
Provides-Extra: cloud
Requires-Dist: openai>=1.0.0; extra == "cloud"
Requires-Dist: anthropic>=0.3.0; extra == "cloud"
Provides-Extra: local
Requires-Dist: ctransformers>=0.2.27; extra == "local"
Provides-Extra: llama
Requires-Dist: llama-cpp-python>=0.2.0; extra == "llama"
Dynamic: author
Dynamic: home-page
Dynamic: license-file
Dynamic: requires-python
